blanc_basic_assets/__init__.py
blanc_basic_assets/admin.py
blanc_basic_assets/apps.py
blanc_basic_assets/fields.py
blanc_basic_assets/listeners.py
blanc_basic_assets/models.py
blanc_basic_assets/tests.py
blanc_basic_assets/migrations/0001_initial.py
blanc_basic_assets/migrations/__init__.py
blanc_basic_assets-0.3.3.dist-info/DESCRIPTION.rst
blanc_basic_assets-0.3.3.dist-info/METADATA
blanc_basic_assets-0.3.3.dist-info/RECORD
blanc_basic_assets-0.3.3.dist-info/WHEEL
blanc_basic_assets-0.3.3.dist-info/metadata.json
blanc_basic_assets-0.3.3.dist-info/top_level.txt
